[
  {
    "id": "id-mocebh26-hihboif",
    "matchRequestId": "id-moce3hxr-l97dt1c",
    "participants": [
      "id-mnsm12ov-kpkaldi",
      "id-moccj45g-ygwkk8x"
    ],
    "scheduledAt": "2026-04-25T04:13:50.238Z",
    "status": "scheduled"
  },
  {
    "id": "id-mol42tlj-kwxmeuc",
    "matchRequestId": "id-mol3vwj6-18qv0a5",
    "participants": [
      "id-mol2g5lb-rvnvuvi",
      "test-walker-001"
    ],
    "scheduledAt": "2026-05-01T06:37:06.007Z",
    "status": "scheduled"
  },
  {
    "id": "id-mol4sxw7-2xsjruj",
    "matchRequestId": "id-mol4phvc-gve480x",
    "participants": [
      "id-mol2g5lb-rvnvuvi",
      "test-walker-001"
    ],
    "scheduledAt": "2026-05-01T06:57:24.631Z",
    "status": "scheduled"
  }
]